skytemple_dtef/__init__.py
skytemple_dtef/dungeon_xml.py
skytemple_dtef/explorers_dtef.py
skytemple_dtef/explorers_dtef_importer.py
skytemple_dtef/rules.py
skytemple_dtef/template.png
skytemple_dtef/transform.py
skytemple_dtef-1.6.1.dist-info/LICENSE
skytemple_dtef-1.6.1.dist-info/METADATA
skytemple_dtef-1.6.1.dist-info/WHEEL
skytemple_dtef-1.6.1.dist-info/top_level.txt
skytemple_dtef-1.6.1.dist-info/RECORD
