Metadata-Version: 2.1
Name: skytemple-dtef
Version: 1.6.1
Summary: Dungeon Tile Exchange Format: A format for standardized rule-based tilesets with 256 adjacency combinations.
Home-page: https://github.com/SkyTemple/skytemple-dtef/
Classifier: Development Status :: 4 - Beta
Classifier: Programming Language :: Python
Classifier: License :: OSI Approved :: GNU General Public License v3 or later (GPLv3+)
Classifier: Programming Language :: Python :: 3.9
Classifier: Programming Language :: Python :: 3.10
Classifier: Programming Language :: Python :: 3.11
Classifier: Programming Language :: Python :: 3.12
License-File: LICENSE
Requires-Dist: skytemple-files >=1.6.0rc1
Requires-Dist: Pillow >=6.1.0
